{"name":"Llenar formulario de árbol con datos válidos","id":"funcionalidad-del-administrador-de-árboles;llenar-formulario-de-árbol-con-datos-válidos","testSteps":[{"number":1,"description":"Given que estoy en la página del administrador","duration":797,"startTime":"2025-06-21T14:10:26.825425500-04:00[America/La_Paz]","result":"SUCCESS","precondition":false,"level":0},{"number":2,"description":"When lleno el formulario con los siguientes datos:\r\n| campo | valor |\r\n| especie | Schinus molle |\r\n| edad | 5 |\r\n| cuidados | Riego semanal |\r\n| estado | nativo |\r\n| fotoUrl | https://example.com/tree.jpg |\r\n| altura | 3.5 |\r\n| diametroTronco | 25.0 |","duration":2243,"startTime":"2025-06-21T14:10:27.625205-04:00[America/La_Paz]","result":"SUCCESS","precondition":false,"level":0},{"number":3,"description":"Then el formulario debe estar completamente lleno","duration":1,"startTime":"2025-06-21T14:10:29.869537600-04:00[America/La_Paz]","result":"SUCCESS","precondition":false,"level":0},{"number":4,"description":"And el botón \"Agregar Árbol\" debe estar habilitado","duration":255,"startTime":"2025-06-21T14:10:29.871051-04:00[America/La_Paz]","result":"SUCCESS","precondition":false,"level":0}],"userStory":{"id":"funcionalidad-del-administrador-de-árboles","storyName":"Funcionalidad del Administrador de Árboles","displayName":"Funcionalidad del Administrador de Árboles","path":"administrador.feature","narrative":"  Como administrador del sistema SkyGreen\n  Quiero poder gestionar la información de los árboles\n  Para mantener actualizada la base de datos de reforestación","type":"feature","qualifiedTag":{"name":"Funcionalidad del Administrador de Árboles","type":"feature","displayName":"Funcionalidad del Administrador de Árboles"}},"featureTag":{"name":"Funcionalidad del Administrador de Árboles","type":"feature","displayName":"Funcionalidad del Administrador de Árboles"},"title":"Llenar formulario de árbol con datos válidos","description":"","backgroundTitle":"","backgroundDescription":"","tags":[{"name":"Windows","type":"context","displayName":"Windows"},{"name":"Funcionalidad del Administrador de Árboles","type":"feature","displayName":"Funcionalidad del Administrador de Árboles"},{"name":"formulario","type":"tag","displayName":"formulario"},{"name":"administrador","type":"tag","displayName":"administrador"}],"allTags":[{"name":"Windows","type":"context","displayName":"Windows"},{"name":"Funcionalidad del Administrador de Árboles","type":"feature","displayName":"Funcionalidad del Administrador de Árboles"},{"name":"formulario","type":"tag","displayName":"formulario"},{"name":"administrador","type":"tag","displayName":"administrador"}],"startTime":"2025-06-21T14:10:25.977949300-04:00[America/La_Paz]","duration":4445,"projectKey":"","isManualTestingUpToDate":false,"context":"windows","manual":false,"testSource":"Cucumber","result":"SUCCESS"}